dispyt/__init__.py
dispyt/base.py
dispyt/exceptions.py
dispyt/struct.py
dispyt-0.0.2b2.dist-info/METADATA
dispyt-0.0.2b2.dist-info/RECORD
dispyt-0.0.2b2.dist-info/WHEEL
dispyt-0.0.2b2.dist-info/top_level.txt
