Metadata-Version: 2.1
Name: dispyt
Version: 0.0.2b2
Summary: 📚 Dispyt is an API wrapper for the Discord API [Python3]
Home-page: https://github.com/truedl/dispyt
Author: truedl
Author-email: dauzduz1@example.com
License: UNKNOWN
Platform: UNKNOWN
Classifier: Programming Language :: Python :: 3
Classifier: License :: OSI Approved :: MIT License
Classifier: Operating System :: OS Independent
Requires-Dist: asyncio
Requires-Dist: aiohttp
Requires-Dist: websockets
